CHANGES.txt
LICENSE.txt
MANIFEST.in
README.txt
TODO.txt
setup.py
src/p01/__init__.py
src/p01.elasticsearch.egg-info/PKG-INFO
src/p01.elasticsearch.egg-info/SOURCES.txt
src/p01.elasticsearch.egg-info/dependency_links.txt
src/p01.elasticsearch.egg-info/namespace_packages.txt
src/p01.elasticsearch.egg-info/not-zip-safe
src/p01.elasticsearch.egg-info/requires.txt
src/p01.elasticsearch.egg-info/top_level.txt
src/p01/elasticsearch/README.txt
src/p01/elasticsearch/__init__.py
src/p01/elasticsearch/bulk.txt
src/p01/elasticsearch/connection.py
src/p01/elasticsearch/exceptions.py
src/p01/elasticsearch/index.txt
src/p01/elasticsearch/interfaces.py
src/p01/elasticsearch/mapping.txt
src/p01/elasticsearch/pool.py
src/p01/elasticsearch/sample.txt
src/p01/elasticsearch/scan.txt
src/p01/elasticsearch/simple.txt
src/p01/elasticsearch/testing.py
src/p01/elasticsearch/tests.py
src/p01/elasticsearch/thrift.txt
src/p01/elasticsearch/config/elasticsearch.yml
src/p01/elasticsearch/config/logging.yml
src/p01/elasticsearch/config/mappings/testing/job.json
src/p01/elasticsearch/sample/config/elasticsearch.yml
src/p01/elasticsearch/sample/config/logging.yml
src/p01/elasticsearch/sample/config/companies/company.json
src/p01/elasticsearch/sample/sandbox/LICENSE.txt
src/p01/elasticsearch/sample/sandbox/NOTICE.txt
src/p01/elasticsearch/sample/sandbox/config/elasticsearch.yml
src/p01/elasticsearch/sample/sandbox/config/logging.yml
src/p01/elasticsearch/sample/sandbox/config/companies/company.json
src/p01/elasticsearch/sandbox/LICENSE.txt
src/p01/elasticsearch/sandbox/NOTICE.txt
src/p01/elasticsearch/sandbox/config/elasticsearch.yml
src/p01/elasticsearch/sandbox/config/logging.yml
src/p01/elasticsearch/sandbox/config/mappings/testing/job.json
src/p01/elasticsearch/thriftconnector/Rest.py
src/p01/elasticsearch/thriftconnector/__init__.py
src/p01/elasticsearch/thriftconnector/constants.py
src/p01/elasticsearch/thriftconnector/simple_test.py
src/p01/elasticsearch/thriftconnector/ttypes.py